slate_db/__init__.py
slate_db/slate_db.py
slate_db-0.1.1.dist-info/METADATA
slate_db-0.1.1.dist-info/WHEEL
slate_db-0.1.1.dist-info/top_level.txt
slate_db-0.1.1.dist-info/RECORD
