Metadata-Version: 2.1
Name: slate-db
Version: 0.1.1
Summary: Wrapper for working with Slate databases.
Home-page: https://github.com/jamie-r-davis/slate_db
Author: Jamie Davis
Author-email: jamjam@umich.edu
License: MIT
Platform: UNKNOWN
Requires-Dist: attrdict
Requires-Dist: pyodbc
